MANIFEST.in
README.md
req.py
requirements.txt
setup.py
algoneer/__init__.py
algoneer/algorithm_test.py
algoneer/dataset_model_test.py
algoneer/dataset_test.py
algoneer/object.py
algoneer/project.py
algoneer/py.typed
algoneer.egg-info/PKG-INFO
algoneer.egg-info/SOURCES.txt
algoneer.egg-info/dependency_links.txt
algoneer.egg-info/entry_points.txt
algoneer.egg-info/not-zip-safe
algoneer.egg-info/requires.txt
algoneer.egg-info/top_level.txt
algoneer/algorithm/__init__.py
algoneer/algorithm/algorithm.py
algoneer/algorithm/sklearn.py
algoneer/algorithmschema/__init__.py
algoneer/algorithmschema/algorithmschema.py
algoneer/api/__init__.py
algoneer/api/algorithm.py
algoneer/api/algorithm_result.py
algoneer/api/algorithmschema.py
algoneer/api/base_client.py
algoneer/api/client.py
algoneer/api/datapoint.py
algoneer/api/datapoint_model_result.py
algoneer/api/dataschema.py
algoneer/api/dataset.py
algoneer/api/dataset_model_result.py
algoneer/api/dataset_result.py
algoneer/api/manager.py
algoneer/api/model.py
algoneer/api/model_result.py
algoneer/api/object.py
algoneer/api/project.py
algoneer/api/response.py
algoneer/api/session.py
algoneer/cli/__init__.py
algoneer/cli/main.py
algoneer/dataschema/__init__.py
algoneer/dataschema/attributeschema.py
algoneer/dataschema/dataschema.py
algoneer/dataset/__init__.py
algoneer/dataset/attribute.py
algoneer/dataset/datapoint.py
algoneer/dataset/dataset.py
algoneer/dataset/pandas.py
algoneer/dataset/roles.py
algoneer/methods/__init__.py
algoneer/methods/blackbox/__init__.py
algoneer/methods/blackbox/adversarial.py
algoneer/methods/blackbox/ale.py
algoneer/methods/blackbox/counterfactual.py
algoneer/methods/blackbox/pdp.py
algoneer/methods/blackbox/predictions.py
algoneer/methods/blackbox/shap.py
algoneer/methods/dataset/__init__.py
algoneer/methods/dataset/anomalies.py
algoneer/methods/dataset/correlations.py
algoneer/methods/dataset/coverage.py
algoneer/methods/dataset/distribution.py
algoneer/methods/dataset/survey.py
algoneer/model/__init__.py
algoneer/model/model.py
algoneer/model/sklearn.py
algoneer/result/__init__.py
algoneer/result/algorithm_result.py
algoneer/result/datapoint_model_result.py
algoneer/result/dataset_model_result.py
