Metadata-Version: 1.2
Name: algoneer
Version: 0.0.12
Summary: A Python toolkit for testing algorithmic systems and machine learning models.
Home-page: https://github.com/algoneer/algoneer
Author: Andreas Dewes
Author-email: authors@algoneer.org
License: MIT
Platform: UNKNOWN
Requires-Python: >=3.6
